qubogen/__init__.py
qubogen/data.py
qubogen/qubo.py
qubogen/utils.py
qubogen-0.1.1.dist-info/LICENSE
qubogen-0.1.1.dist-info/METADATA
qubogen-0.1.1.dist-info/WHEEL
qubogen-0.1.1.dist-info/top_level.txt
qubogen-0.1.1.dist-info/RECORD
