Metadata-Version: 2.1
Name: qubogen
Version: 0.1.1
Summary: QUBO matrix generator on major combinatorial optimization problems written in Python
Home-page: https://github.com/tamuhey/qubogen
Author: tamuhey
Author-email: tamuhey@gmail.com
License: MIT
Keywords: qubo,combinatorial optimization
Platform: UNKNOWN
Requires-Python: >=3.7
Requires-Dist: networkx (>=2.2)
